lektor_root_relative_path/__init__.py
lektor_root_relative_path-0.1.dist-info/DESCRIPTION.rst
lektor_root_relative_path-0.1.dist-info/METADATA
lektor_root_relative_path-0.1.dist-info/RECORD
lektor_root_relative_path-0.1.dist-info/WHEEL
lektor_root_relative_path-0.1.dist-info/entry_points.txt
lektor_root_relative_path-0.1.dist-info/metadata.json
lektor_root_relative_path-0.1.dist-info/top_level.txt
