Metadata-Version: 2.0
Name: lektor-root-relative-path
Version: 0.1
Summary: Root relative path plugin for Lektor
Home-page: http://github.com/a2csuga/lektor-root-relative-path
Author: Atsushi Suga
Author-email: a2csuga@users.noreply.github.com
License: MIT
Platform: UNKNOWN
